{
  "tables": {
    "student": {
      "name": "student",
      "columns": [
        {
          "name": "name",
          "type": "type",
          "constraints": "constraints"
        },
        {
          "name": "name",
          "type": "type",
          "constraints": "constraints"
        },
        {
          "name": "name",
          "type": "type",
          "constraints": "constraints"
        }
      ],
      "created_at": "2025-09-09T19:43:09.477613",
      "row_count": 0
    },
    "customers": {
      "name": "customers",
      "columns": [
        {
          "name": "name",
          "type": "type",
          "constraints": "constraints"
        },
        {
          "name": "name",
          "type": "type",
          "constraints": "constraints"
        },
        {
          "name": "name",
          "type": "type",
          "constraints": "constraints"
        },
        {
          "name": "name",
          "type": "type",
          "constraints": "constraints"
        }
      ],
      "created_at": "2025-09-09T22:37:45.346337",
      "row_count": 0
    },
    "users": {
      "name": "users",
      "columns": [
        {
          "name": "name",
          "type": "type",
          "constraints": "constraints"
        },
        {
          "name": "name",
          "type": "type",
          "constraints": "constraints"
        },
        {
          "name": "name",
          "type": "type",
          "constraints": "constraints"
        }
      ],
      "created_at": "2025-09-10T00:27:48.354560",
      "row_count": 0
    },
    "test_dml": {
      "name": "test_dml",
      "columns": [
        {
          "name": "name",
          "type": "type",
          "constraints": "constraints"
        },
        {
          "name": "name",
          "type": "type",
          "constraints": "constraints"
        },
        {
          "name": "name",
          "type": "type",
          "constraints": "constraints"
        }
      ],
      "created_at": "2025-09-10T00:28:14.628830",
      "row_count": 0
    },
    "test_dml1": {
      "name": "test_dml1",
      "columns": [
        {
          "name": "name",
          "type": "type",
          "constraints": "constraints"
        },
        {
          "name": "name",
          "type": "type",
          "constraints": "constraints"
        },
        {
          "name": "name",
          "type": "type",
          "constraints": "constraints"
        }
      ],
      "created_at": "2025-09-10T00:43:42.266792",
      "row_count": 0
    },
    "products": {
      "name": "products",
      "columns": [
        {
          "name": "name",
          "type": "type",
          "constraints": "constraints"
        },
        {
          "name": "name",
          "type": "type",
          "constraints": "constraints"
        },
        {
          "name": "name",
          "type": "type",
          "constraints": "constraints"
        }
      ],
      "created_at": "2025-09-10T01:01:08.597057",
      "row_count": 0
    },
    "product": {
      "name": "product",
      "columns": [
        {
          "name": "product_id",
          "type": "INT",
          "constraints": null
        },
        {
          "name": "name",
          "type": "VARCHAR(50)",
          "constraints": null
        },
        {
          "name": "category",
          "type": "VARCHAR(30)",
          "constraints": null
        },
        {
          "name": "price",
          "type": "INT",
          "constraints": null
        }
      ],
      "created_at": "2025-09-10T01:26:55.246713",
      "row_count": 0
    },
    "test_dml2": {
      "name": "test_dml2",
      "columns": [
        {
          "name": "id",
          "type": "INT",
          "constraints": null
        },
        {
          "name": "name",
          "type": "VARCHAR(50)",
          "constraints": null
        },
        {
          "name": "value",
          "type": "INT",
          "constraints": null
        }
      ],
      "created_at": "2025-09-10T10:21:29.663751",
      "row_count": 0
    },
    "test_dml4": {
      "name": "test_dml4",
      "columns": [
        {
          "name": "id",
          "type": "INT",
          "constraints": null
        },
        {
          "name": "name",
          "type": "VARCHAR(50)",
          "constraints": null
        },
        {
          "name": "value",
          "type": "INT",
          "constraints": null
        }
      ],
      "created_at": "2025-09-10T10:34:14.175428",
      "row_count": 0
    },
    "customer": {
      "name": "customer",
      "columns": [
        {
          "name": "customer_id",
          "type": "INT",
          "constraints": null
        },
        {
          "name": "name",
          "type": "VARCHAR(50)",
          "constraints": null
        },
        {
          "name": "city",
          "type": "VARCHAR(30)",
          "constraints": null
        },
        {
          "name": "age",
          "type": "INT",
          "constraints": null
        }
      ],
      "created_at": "2025-09-10T14:16:17.969090",
      "row_count": 0
    },
    "orders": {
      "name": "orders",
      "columns": [
        {
          "name": "order_id",
          "type": "INT",
          "constraints": null
        },
        {
          "name": "customer_id",
          "type": "INT",
          "constraints": null
        },
        {
          "name": "amount",
          "type": "INT",
          "constraints": null
        },
        {
          "name": "order_date",
          "type": "VARCHAR(20)",
          "constraints": null
        }
      ],
      "created_at": "2025-09-10T15:31:22.935943",
      "row_count": 0
    },
    "orders1": {
      "name": "orders1",
      "columns": [
        {
          "name": "order_id",
          "type": "INT",
          "constraints": null
        },
        {
          "name": "customer_id",
          "type": "INT",
          "constraints": null
        },
        {
          "name": "amount",
          "type": "INT",
          "constraints": null
        },
        {
          "name": "order_date",
          "type": "VARCHAR(20)",
          "constraints": null
        }
      ],
      "created_at": "2025-09-10T15:33:54.665878",
      "row_count": 0
    },
    "customers1": {
      "name": "customers1",
      "columns": [
        {
          "name": "customer_id",
          "type": "INT",
          "constraints": null
        },
        {
          "name": "name",
          "type": "VARCHAR(50)",
          "constraints": null
        },
        {
          "name": "city",
          "type": "VARCHAR(30)",
          "constraints": null
        },
        {
          "name": "age",
          "type": "INT",
          "constraints": null
        }
      ],
      "created_at": "2025-09-10T16:07:23.996640",
      "row_count": 0
    },
    "students": {
      "name": "students",
      "columns": [
        {
          "name": "id",
          "type": "INT",
          "constraints": null
        },
        {
          "name": "name",
          "type": "VARCHAR(50)",
          "constraints": null
        },
        {
          "name": "major",
          "type": "VARCHAR(30)",
          "constraints": null
        },
        {
          "name": "gpa",
          "type": "INT",
          "constraints": null
        }
      ],
      "created_at": "2025-09-10T16:30:57.522400",
      "row_count": 0
    },
    "courses": {
      "name": "courses",
      "columns": [
        {
          "name": "course_id",
          "type": "INT",
          "constraints": null
        },
        {
          "name": "course_name",
          "type": "VARCHAR(50)",
          "constraints": null
        },
        {
          "name": "credits",
          "type": "INT",
          "constraints": null
        }
      ],
      "created_at": "2025-09-10T16:31:05.936689",
      "row_count": 0
    },
    "enrollments": {
      "name": "enrollments",
      "columns": [
        {
          "name": "student_id",
          "type": "INT",
          "constraints": null
        },
        {
          "name": "course_id",
          "type": "INT",
          "constraints": null
        },
        {
          "name": "grade",
          "type": "VARCHAR(2)",
          "constraints": null
        }
      ],
      "created_at": "2025-09-10T16:31:16.649315",
      "row_count": 0
    },
    "customers2": {
      "name": "customers2",
      "columns": [
        {
          "name": "customer_id",
          "type": "INT",
          "constraints": null
        },
        {
          "name": "name",
          "type": "VARCHAR(50)",
          "constraints": null
        },
        {
          "name": "city",
          "type": "VARCHAR(30)",
          "constraints": null
        },
        {
          "name": "age",
          "type": "INT",
          "constraints": null
        }
      ],
      "created_at": "2025-09-10T22:55:58.831735",
      "row_count": 0
    },
    "orders2": {
      "name": "orders2",
      "columns": [
        {
          "name": "order_id",
          "type": "INT",
          "constraints": null
        },
        {
          "name": "customer_id",
          "type": "INT",
          "constraints": null
        },
        {
          "name": "amount",
          "type": "INT",
          "constraints": null
        },
        {
          "name": "order_date",
          "type": "VARCHAR(20)",
          "constraints": null
        }
      ],
      "created_at": "2025-09-10T22:56:16.738664",
      "row_count": 0
    },
    "products2": {
      "name": "products2",
      "columns": [
        {
          "name": "product_id",
          "type": "INT",
          "constraints": null
        },
        {
          "name": "name",
          "type": "VARCHAR(50)",
          "constraints": null
        },
        {
          "name": "category",
          "type": "VARCHAR(30)",
          "constraints": null
        },
        {
          "name": "price",
          "type": "INT",
          "constraints": null
        }
      ],
      "created_at": "2025-09-10T22:56:34.826137",
      "row_count": 0
    }
  },
  "metadata": {
    "version": "1.0",
    "created_at": null
  }
}